[
  {
    "id": "1",
    "type": "outgoing",
    "bank": "Chase",
    "description": "Rent",
    "amount": 1200,
    "startMonth": "2024-01",
    "reflection": 30,
    "cycles": 0
  },
  {
    "id": "2",
    "type": "outgoing",
    "bank": "Chase",
    "description": "Utilities",
    "amount": 150,
    "startMonth": "2024-01",
    "reflection": 15,
    "cycles": 0
  },
  {
    "id": "3",
    "type": "incoming",
    "description": "Salary",
    "amount": 5000,
    "startMonth": "2024-01",
    "reflection": 30,
    "cycles": 0
  }
]